log/__init__.py
retrotv_log-0.0.6a0.dist-info/licenses/LICENSE
retrotv_log-0.0.6a0.dist-info/METADATA
retrotv_log-0.0.6a0.dist-info/WHEEL
retrotv_log-0.0.6a0.dist-info/top_level.txt
retrotv_log-0.0.6a0.dist-info/RECORD
